django_unmigrate/__init__.py
django_unmigrate/core.py
django_unmigrate/management/__init__.py
django_unmigrate/management/commands/__init__.py
django_unmigrate/management/commands/unmigrate.py
django_unmigrate-0.3.1.dist-info/LICENSE
django_unmigrate-0.3.1.dist-info/WHEEL
django_unmigrate-0.3.1.dist-info/METADATA
django_unmigrate-0.3.1.dist-info/RECORD
