Metadata-Version: 2.1
Name: django-unmigrate
Version: 0.3.1
Summary: Smart reversion of Django migrations based on Git diff
Home-page: https://github.com/lorinkoz/django-unmigrate
License: MIT
Keywords: django,git,migrations
Author: Lorenzo Peña
Author-email: lorinkoz@gmail.com
Requires-Python: >=3.6.2,<4.0.0
Classifier: Development Status :: 4 - Beta
Classifier: Framework :: Django
Classifier: Framework :: Django :: 2.0
Classifier: Framework :: Django :: 2.1
Classifier: Framework :: Django :: 2.2
Classifier: Framework :: Django :: 3.0
Classifier: Framework :: Django :: 3.1
Classifier: Framework :: Django :: 3.2
Classifier: License :: OSI Approved :: MIT License
Classifier: Programming Language :: Python :: 3
Classifier: Programming Language :: Python :: 3.10
Classifier: Programming Language :: Python :: 3.7
Classifier: Programming Language :: Python :: 3.8
Classifier: Programming Language :: Python :: 3.9
Requires-Dist: GitPython (>=3.1.13,<4.0.0)
Requires-Dist: django (>=2.0)
Project-URL: Repository, https://github.com/lorinkoz/django-unmigrate
